pytorch_resample/__init__.py
pytorch_resample/hybrid.py
pytorch_resample/over.py
pytorch_resample/under.py
pytorch_resample/utils.py
pytorch_resample-0.1.0.dist-info/LICENSE
pytorch_resample-0.1.0.dist-info/WHEEL
pytorch_resample-0.1.0.dist-info/METADATA
pytorch_resample-0.1.0.dist-info/RECORD
