Metadata-Version: 2.1
Name: pytorch-resample
Version: 0.1.0
Summary: Resampling methods for iterable datasets in PyTorch
Author: Max Halford
Author-email: maxhalford25@gmail.com
Requires-Python: >=3.6.1,<4.0.0
Classifier: Programming Language :: Python :: 3
Classifier: Programming Language :: Python :: 3.7
Classifier: Programming Language :: Python :: 3.8
Requires-Dist: torch (>=1.6.0,<2.0.0)
